.DS_Store
methylcheck/QCreport.py
methylcheck/__init__.py
methylcheck/__main__.py
methylcheck/cli.py
methylcheck/filters.py
methylcheck/load_processed.py
methylcheck/p_value_probe_detection.py
methylcheck/postprocessQC.py
methylcheck/progress_bar.py
methylcheck/qc_plot.py
methylcheck/qc_report.py
methylcheck/rawQC.py
methylcheck/read_geo_processed.py
methylcheck/version.py
methylcheck/data_files/450k_Sesame.txt.gz
methylcheck/data_files/450k_control.npy
methylcheck/data_files/450k_extC.csv
methylcheck/data_files/450k_extT.csv
methylcheck/data_files/450k_polymorphic_crossRxtve_probes.csv.gz
methylcheck/data_files/450k_sex.npy
methylcheck/data_files/EPIC+_control.npy
methylcheck/data_files/EPIC+_sex.npy
methylcheck/data_files/EPIC_Sesame.txt.gz
methylcheck/data_files/EPIC_control.npy
methylcheck/data_files/EPIC_polymorphic_crossRxtve_probes.csv.gz
methylcheck/data_files/EPIC_sex.npy
methylcheck/data_files/__init__.py
methylcheck/data_files/epic_extC.csv
methylcheck/data_files/epic_extT.csv
methylcheck/data_files/illumina_sketchy_probes_996.npy
methylcheck/data_files/mouse_extC.csv
methylcheck/data_files/mouse_extT.csv
methylcheck/data_files/mouse_strain_snps.csv
methylcheck/data_files/toFlip.csv
methylcheck/predict/__init__.py
methylcheck/predict/ethnicity.py
methylcheck/predict/sex.py
methylcheck/predict/strain.py
methylcheck/probes/__init__.py
methylcheck/probes/filters.py
methylcheck/reports/__init__.py
methylcheck/reports/bead_array.py
methylcheck/reports/qc_report.py
methylcheck/samples/__init__.py
methylcheck/samples/assign.py
methylcheck/samples/assign_groups.py
methylcheck/samples/postprocessQC.py
methylcheck/samples/sklearn_mds.py
methylcheck-0.8.5.dist-info/LICENSE
methylcheck-0.8.5.dist-info/METADATA
methylcheck-0.8.5.dist-info/WHEEL
methylcheck-0.8.5.dist-info/entry_points.txt
methylcheck-0.8.5.dist-info/top_level.txt
methylcheck-0.8.5.dist-info/RECORD
