Metadata-Version: 2.1
Name: methylcheck
Version: 0.8.5
Summary: Quality Control (QC), Visualization/plotting, and postprocessing software for Illumina methylation array data. See https://life-epigenetics-methylcheck.readthedocs-hosted.com/en/latest/ for full documentation and examples.
Home-page: https://github.com/FOXOBioScience/methylcheck
Author: Life Epigenetics
Author-email: info@FOXOBioScience.com
License: MIT License
Project-URL: Documentation, https://life-epigenetics-methylcheck.readthedocs-hosted.com/en/latest/
Project-URL: Source, https://github.com/FOXOBioScience/methylcheck/
Project-URL: Funding, https://FOXOBioScience.com/
Keywords: methylation dna data processing epigenetics illumina
Platform: UNKNOWN
Classifier: Development Status :: 5 - Production/Stable
Classifier: Environment :: Console
Classifier: License :: OSI Approved :: MIT License
Classifier: Programming Language :: Python :: 3.7
Classifier: Topic :: Scientific/Engineering :: Bio-Informatics
Classifier: Topic :: Scientific/Engineering :: Medical Science Apps.
Classifier: Framework :: Jupyter
Classifier: Intended Audience :: Science/Research
Classifier: Intended Audience :: Financial and Insurance Industry
Classifier: Operating System :: MacOS :: MacOS X
Classifier: Operating System :: Microsoft :: Windows
Classifier: Operating System :: POSIX :: Linux
Requires-Dist: numpy
Requires-Dist: pandas (>=1.3.0)
Requires-Dist: statsmodels
Requires-Dist: matplotlib
Requires-Dist: seaborn
Requires-Dist: tqdm
Requires-Dist: joblib
Requires-Dist: scikit-learn
Requires-Dist: xlsxwriter
Requires-Dist: openpyxl
Provides-Extra: dev
Requires-Dist: methylprep ; extra == 'dev'
Requires-Dist: pytest ; extra == 'dev'
Requires-Dist: pytest-pep8 ; extra == 'dev'
Requires-Dist: pytest-cov ; extra == 'dev'
Requires-Dist: flake8 ; extra == 'dev'
Requires-Dist: coverage ; extra == 'dev'
Requires-Dist: xlrd ; extra == 'dev'
Requires-Dist: coveralls ; extra == 'dev'
Requires-Dist: sphinxcontrib-apidoc ; extra == 'dev'
Requires-Dist: m2r ; extra == 'dev'
Requires-Dist: nbsphinx ; extra == 'dev'
Requires-Dist: sphinx ; extra == 'dev'
Requires-Dist: ipykernel ; extra == 'dev'
Requires-Dist: fastparquet ; extra == 'dev'
